safepandas/__init__.py
safepandas/encryption.py
safepandas/example.py
safepandas/safepandas.py
safepandas-0.0.5.dist-info/LICENSE
safepandas-0.0.5.dist-info/METADATA
safepandas-0.0.5.dist-info/WHEEL
safepandas-0.0.5.dist-info/top_level.txt
safepandas-0.0.5.dist-info/RECORD
