Metadata-Version: 2.2
Name: safepandas
Version: 0.0.5
Summary: Securing pandas with homomorphic encryption
Author: Your Name
Author-email: Abhyudit Bisht <bisht.dit@gmail.com>
License: MIT
Project-URL: Homepage, https://github.com/bishtabhyudit/safepandas
Project-URL: Issues, https://github.com/bishtabhyudit/safepandas/issues
Classifier: Programming Language :: Python :: 3
Classifier: Operating System :: OS Independent
Requires-Python: >=3.7
License-File: LICENSE
Requires-Dist: pandas
Requires-Dist: pyseal
Requires-Dist: cryptography
Dynamic: author
Dynamic: requires-python
